{"state": "co", "upper": [{"id": "COL000005", "name": "Cheri Jahn", "accounts": [{"type": "Twitter", "id": "cherijahn"}]}, {"id": "COL000018", "name": "Kent Lambert", "accounts": [{"type": "Twitter", "id": "KentLambert"}, {"type": "Facebook", "id": "senatorlambert"}, {"type": "Facebook", "id": "senatorlambert"}]}, {"id": "COL000024", "name": "Kevin Lundberg", "accounts": [{"type": "Twitter", "id": "KevinLundberg"}, {"type": "Facebook", "id": "kevin.lundberg1"}]}, {"id": "COL000033", "name": "Lucia Guzman", "accounts": [{"type": "Twitter", "id": "SenGuzman"}]}, {"id": "COL000035", "name": "Irene Aguilar", "accounts": [{"type": "Twitter", "id": "AguilarFor32"}]}, {"id": "COL000037", "name": "Ray Scott", "accounts": [{"type": "Twitter", "id": "SCOTTFORCOLO"}]}, {"id": "COL000045", "name": "Jerry Sonnenberg", "accounts": [{"type": "Twitter", "id": "JerrySonnenberg"}, {"type": "Facebook", "id": "RepSonnenberg"}, {"type": "YouTube", "id": "RepSonnenberg"}]}, {"id": "COL000057", "name": "Chris Holbert", "accounts": [{"type": "Twitter", "id": "Chris_Holbert"}, {"type": "Facebook", "id": "chris.holbert.18"}]}, {"id": "COL000062", "name": "Nancy Todd", "accounts": [{"type": "Twitter", "id": "nancytodd28"}]}, {"id": "COL000069", "name": "Angela Williams", "accounts": [{"type": "Twitter", "id": "COSenWilliams"}]}, {"id": "COL000082", "name": "Matt Jones", "accounts": [{"type": "Twitter", "id": "MattJonesCO"}]}, {"id": "COL000094", "name": "John Kefalas", "accounts": [{"type": "Twitter", "id": "KefalasJohn"}]}, {"id": "COL000099", "name": "Randy Baumgardner", "accounts": [{"type": "Twitter", "id": "CapitalCowboy"}, {"type": "Facebook", "id": "randy.baumgardner.94"}]}, {"id": "COL000104", "name": "Vicki Marble", "accounts": [{"type": "Facebook", "id": "senvicki.marble"}, {"type": "Twitter", "id": "VickiMarble"}, {"type": "YouTube", "id": "VickiMarble2012"}]}, {"id": "COL000107", "name": "Owen Hill", "accounts": [{"type": "Twitter", "id": "owenjhill"}]}, {"id": "COL000111", "name": "Larry Crowder", "accounts": [{"type": "Twitter", "id": "SenatorCrowder"}]}, {"id": "COL000148", "name": "Andy Kerr", "accounts": [{"type": "Twitter", "id": "SenAndyKerr"}]}, {"id": "COL000165", "name": "Jack Tate", "accounts": [{"type": "Twitter", "id": "JackTateCO"}]}, {"id": "COL000174", "name": "Beth Martinez Humenik", "accounts": [{"type": "Twitter", "id": "Beth4HD31"}]}, {"id": "COL000182", "name": "Leroy Garcia", "accounts": [{"type": "Facebook", "id": "leroy.j.garcia.7"}, {"type": "Twitter", "id": "Leroy_Garcia"}]}, {"id": "COL000185", "name": "John Cooke", "accounts": [{"type": "Facebook", "id": "JohnCookeForColoradoSD13"}, {"type": "Twitter", "id": "JohnCooke4SD13"}]}, {"id": "COL000186", "name": "Kerry Donovan", "accounts": [{"type": "Twitter", "id": "KerryDonovanSD5"}]}, {"id": "COL000192", "name": "Michael Merrifield", "accounts": [{"type": "Twitter", "id": "merrifield_sd11"}]}, {"id": "COL000194", "name": "Tim Neville", "accounts": [{"type": "Twitter", "id": "NevilleforCO"}]}, {"id": "COL000222", "name": "Stephen Fenberg", "accounts": [{"type": "Twitter", "id": "SteveFenberg"}]}, {"id": "COL000228", "name": "Lois Court", "accounts": []}, {"id": "COL000229", "name": "Rachel Zenzinger", "accounts": [{"type": "Twitter", "id": "Zenzinger_AtoZ"}]}, {"id": "COL000230", "name": "Kevin Priola", "accounts": [{"type": "Twitter", "id": "KevinPriola"}, {"type": "Facebook", "id": "kevin.priola"}]}, {"id": "COL000232", "name": "Dominick Moreno", "accounts": [{"type": "Twitter", "id": "domoreno"}]}, {"id": "COL000234", "name": "Daniel Kagan", "accounts": [{"type": "Twitter", "id": "DanielKagan"}, {"type": "YouTube", "id": "DanKagan"}]}, {"id": "COL000237", "name": "Jim Smallwood", "accounts": [{"type": "Twitter", "id": "jimsmallwood"}]}, {"id": "COL000241", "name": "Kevin Grantham", "accounts": [{"type": "Twitter", "id": "SenatorGrantham"}]}, {"id": "COL000244", "name": "Bob Gardner", "accounts": [{"type": "Twitter", "id": "SenBobGardner"}]}, {"id": "COL000247", "name": "Don Coram", "accounts": [{"type": "Facebook", "id": "representative.coram"}]}, {"id": "COL000248", "name": "Rhonda Fields", "accounts": [{"type": "Facebook", "id": "pg"}, {"type": "Twitter", "id": "senrhondafields"}]}], "lower": [{"id": "COL000043", "name": "Jon Becker", "accounts": [{"type": "Twitter", "id": "RepJBecker"}, {"type": "Facebook", "id": "jon.becker.581"}]}, {"id": "COL000067", "name": "Crisanta Duran", "accounts": [{"type": "Facebook", "id": "crisanta.duran"}, {"type": "Twitter", "id": "crisantaduran"}]}, {"id": "COL000068", "name": "Daniel Pabon", "accounts": [{"type": "Twitter", "id": "Dan_Pabon"}]}, {"id": "COL000088", "name": "Pete Lee", "accounts": [{"type": "Twitter", "id": "PeteLeeColorado"}, {"type": "Facebook", "id": "peteleeco"}]}, {"id": "COL000090", "name": "Millie Hamner", "accounts": [{"type": "Facebook", "id": "milliehamner"}, {"type": "Twitter", "id": "millie_hamner"}]}, {"id": "COL000100", "name": "Dave Young", "accounts": [{"type": "Facebook", "id": "StateRepresentativeDaveYoung"}]}, {"id": "COL000114", "name": "Brittany Pettersen", "accounts": [{"type": "Twitter", "id": "RepPettersen"}, {"type": "YouTube", "id": "UCKwhDYxAAn3Hi9Vt_iwOXSg"}]}, {"id": "COL000115", "name": "Tracy Kraft-Tharp", "accounts": [{"type": "Twitter", "id": "tkth"}, {"type": "Facebook", "id": "TracyKraftTharp"}]}, {"id": "COL000118", "name": "Lori Saine", "accounts": [{"type": "Twitter", "id": "lorisaine"}]}, {"id": "COL000124", "name": "Lois Landgraf", "accounts": [{"type": "Twitter", "id": "lorisaine"}, {"type": "Facebook", "id": "LandgrafForJobs"}]}, {"id": "COL000125", "name": "Justin Everett", "accounts": [{"type": "Twitter", "id": "RepEverett"}, {"type": "Facebook", "id": "RepresentativeEverett"}, {"type": "YouTube", "id": "EverettForColorado"}]}, {"id": "COL000129", "name": "Jovan Melton", "accounts": [{"type": "Twitter", "id": "JovanMelton"}, {"type": "Facebook", "id": "jovan.melton"}]}, {"id": "COL000130", "name": "Paul Rosenthal", "accounts": [{"type": "Facebook", "id": "prosenthal.teacher"}, {"type": "Twitter", "id": "rosenthal5280"}]}, {"id": "COL000131", "name": "Perry Buck", "accounts": [{"type": "Twitter", "id": "perrybuck49"}, {"type": "Facebook", "id": "perry.buck.14"}, {"type": "Facebook", "id": "perryforcolorado"}]}, {"id": "COL000132", "name": "Polly Lawrence", "accounts": [{"type": "Twitter", "id": "PollyLawrenceCO"}, {"type": "Facebook", "id": "pollylawrencecolorado"}]}, {"id": "COL000133", "name": "Steve Lebsock", "accounts": [{"type": "Twitter", "id": "RepLebsock"}]}, {"id": "COL000135", "name": "Jonathan Singer", "accounts": [{"type": "Facebook", "id": "Singer4House"}, {"type": "Twitter", "id": "Singer4Colorado"}]}, {"id": "COL000136", "name": "Mike Foote", "accounts": [{"type": "Twitter", "id": "RepMikeFoote"}]}, {"id": "COL000143", "name": "Joann Ginal", "accounts": [{"type": "Twitter", "id": "joannginal"}]}, {"id": "COL000146", "name": "Stephen Humphrey", "accounts": [{"type": "Twitter", "id": "SteveHumphrey48"}]}, {"id": "COL000147", "name": "Bob Rankin", "accounts": [{"type": "Twitter", "id": "votebobrankin"}]}, {"id": "COL000161", "name": "KC Becker", "accounts": [{"type": "Twitter", "id": "kcbecker"}]}, {"id": "COL000163", "name": "Susan Lontine", "accounts": [{"type": "Twitter", "id": "LontineHD1"}, {"type": "Facebook", "id": "susanlontineforhd1"}]}, {"id": "COL000164", "name": "Alec Garnett", "accounts": [{"type": "Twitter", "id": "AlecGarnett"}, {"type": "Facebook", "id": "alec.garnett.9"}]}, {"id": "COL000168", "name": "Jeni James Arndt", "accounts": [{"type": "Twitter", "id": "RepJeniArndt"}, {"type": "Facebook", "id": "JeniArndtForColorado"}]}, {"id": "COL000169", "name": "Faith Winter", "accounts": [{"type": "Twitter", "id": "FaithKWinter"}, {"type": "Facebook", "id": "faith.winter"}, {"type": "Facebook", "id": "repfaithwinter"}]}, {"id": "COL000175", "name": "Patrick Neville", "accounts": [{"type": "Twitter", "id": "PatrickForCO"}, {"type": "Facebook", "id": "PatrickforColorado"}, {"type": "Facebook", "id": "patrick.neville.940"}]}, {"id": "COL000178", "name": "Kevin Van Winkle", "accounts": [{"type": "Twitter", "id": "RepKVW"}, {"type": "Facebook", "id": "kevin.vanwinkle43"}]}, {"id": "COL000179", "name": "Yeulin Willett", "accounts": [{"type": "Facebook", "id": "elect.willett"}]}, {"id": "COL000183", "name": "Jessie Danielson", "accounts": [{"type": "Twitter", "id": "jessiedanielson"}, {"type": "Facebook", "id": "jessiedanielsonforcolorado"}]}, {"id": "COL000184", "name": "Terri Carver", "accounts": [{"type": "Facebook", "id": "carverforcolorado"}, {"type": "Twitter", "id": "Terri_Carver"}]}, {"id": "COL000187", "name": "Dan Thurlow", "accounts": [{"type": "Twitter", "id": "dan_thurlow"}, {"type": "Facebook", "id": "DanThurlow55"}]}, {"id": "COL000188", "name": "Kim Ransom", "accounts": [{"type": "Twitter", "id": "KimRansom"}, {"type": "Facebook", "id": "Ransom4HD44"}]}, {"id": "COL000189", "name": "Paul Lundeen", "accounts": [{"type": "Twitter", "id": "Paul_Lundeen"}, {"type": "Facebook", "id": "LundeenPaul"}]}, {"id": "COL000191", "name": "Daneya Esgar", "accounts": [{"type": "Twitter", "id": "Dlesgar"}, {"type": "Facebook", "id": "daneyaesgarHD46"}]}, {"id": "COL000198", "name": "Lang Sias", "accounts": [{"type": "Facebook", "id": "langsias"}]}, {"id": "COL000202", "name": "Cole Wist", "accounts": [{"type": "Twitter", "id": "colewist"}, {"type": "Facebook", "id": "cole.wist"}]}, {"id": "COL000205", "name": "Timothy Leonard", "accounts": []}, {"id": "COL000214", "name": "Edie Hooton", "accounts": [{"type": "Twitter", "id": "ediehooton"}, {"type": "YouTube", "id": "UCmur4KkHdLbfh_pPL39SkFA"}, {"type": "Facebook", "id": "ediehooton"}]}, {"id": "COL000215", "name": "Chris Kennedy", "accounts": [{"type": "Facebook", "id": "kennedy4co"}, {"type": "Twitter", "id": "kennedy4co"}]}, {"id": "COL000216", "name": "Marc Catlin", "accounts": []}, {"id": "COL000217", "name": "Matt Gray", "accounts": [{"type": "Twitter", "id": "matthewogray"}]}, {"id": "COL000218", "name": "Chris Hansen", "accounts": []}, {"id": "COL000219", "name": "Hugh McKean", "accounts": [{"type": "Twitter", "id": "hmckean"}]}, {"id": "COL000220", "name": "Susan Beckman", "accounts": [{"type": "Facebook", "id": "Susan.Beckman38"}, {"type": "Twitter", "id": "SusanBeckman38"}]}, {"id": "COL000221", "name": "Adrienne Benavidez", "accounts": [{"type": "Twitter", "id": "benavidezhd32"}, {"type": "Facebook", "id": "repbenavidezhd32"}]}, {"id": "COL000223", "name": "Joseph Salazar", "accounts": [{"type": "YouTube", "id": "UC31_5TKQ4JgftyzvXao4jbg"}, {"type": "Facebook", "id": "joseph.salazar.7712"}]}, {"id": "COL000225", "name": "Mike Weissman", "accounts": [{"type": "Twitter", "id": "mjweissman"}, {"type": "Facebook", "id": "mike4rep"}]}, {"id": "COL000226", "name": "James Coleman", "accounts": [{"type": "Twitter", "id": "repjamescoleman"}]}, {"id": "COL000227", "name": "Kimmi Lewis", "accounts": []}, {"id": "COL000231", "name": "Larry Liston", "accounts": []}, {"id": "COL000233", "name": "Barbara McLachlan", "accounts": [{"type": "Twitter", "id": "barbaraforco"}]}, {"id": "COL000235", "name": "Donald Valdez", "accounts": [{"type": "Twitter", "id": "donaldvaldezco"}]}, {"id": "COL000236", "name": "James Wilson", "accounts": []}, {"id": "COL000238", "name": "Dominique Jackson", "accounts": [{"type": "Twitter", "id": "Jackson4CO"}]}, {"id": "COL000239", "name": "Jeff Bridges", "accounts": [{"type": "Twitter", "id": "jeffbridges"}, {"type": "Facebook", "id": "bridgesforcolorado"}]}, {"id": "COL000240", "name": "Dafna Michaelson Jenet", "accounts": [{"type": "Twitter", "id": "dafna_m"}, {"type": "YouTube", "id": "UC1nNqPmfYm0UcrxCwQ_y3HQ"}]}, {"id": "COL000242", "name": "Janet Buckner", "accounts": [{"type": "Twitter", "id": "repjanetbuckner"}]}, {"id": "COL000243", "name": "Tony Exum", "accounts": []}, {"id": "COL000245", "name": "Leslie Herod", "accounts": [{"type": "Twitter", "id": "leslieherod"}]}, {"id": "COL000246", "name": "Phil Covarrubias", "accounts": [{"type": "Twitter", "id": "philipacovarru2"}]}, {"id": "COL000249", "name": "Dave Williams", "accounts": [{"type": "Twitter", "id": "RepDaveWilliams"}]}, {"id": "COL000264", "name": "Dylan Roberts", "accounts": []}, {"id": "COL000265", "name": "Judy Reyher", "accounts": [{"type": "Twitter", "id": "ClariceHD47"}]}]}